wagtailmetadata/__init__.py
wagtailmetadata/models.py
wagtailmetadata/locale/.gitkeep
wagtailmetadata/locale/ru/LC_MESSAGES/django.mo
wagtailmetadata/locale/ru/LC_MESSAGES/django.po
wagtailmetadata/tests/__init__.py
wagtailmetadata/tests/conftest.py
wagtailmetadata/tests/models.py
wagtailmetadata/tests/settings.py
wagtailmetadata/tests/test_mixin.py
wagtailmetadata/tests/urls.py
wagtailmetadata/tests/migrations/0001_initial.py
wagtailmetadata/tests/migrations/__init__.py
wagtailmetadata/tests/testapp/__init__.py
wagtail_metadata_mixin-2.0.2.dist-info/LICENSE
wagtail_metadata_mixin-2.0.2.dist-info/METADATA
wagtail_metadata_mixin-2.0.2.dist-info/WHEEL
wagtail_metadata_mixin-2.0.2.dist-info/top_level.txt
wagtail_metadata_mixin-2.0.2.dist-info/RECORD
